MANIFEST.in
README.rst
requirements.txt
setup.py
SimpleGUICS2Pygame/__init__.py
SimpleGUICS2Pygame/codeskulptor.py
SimpleGUICS2Pygame/codeskulptor_lib.py
SimpleGUICS2Pygame/numeric.py
SimpleGUICS2Pygame/simplegui_lib.py
SimpleGUICS2Pygame/simplegui_lib_draw.py
SimpleGUICS2Pygame/simplegui_lib_fps.py
SimpleGUICS2Pygame/simplegui_lib_keys.py
SimpleGUICS2Pygame/simplegui_lib_loader.py
SimpleGUICS2Pygame/simpleplot.py
SimpleGUICS2Pygame.egg-info/PKG-INFO
SimpleGUICS2Pygame.egg-info/SOURCES.txt
SimpleGUICS2Pygame.egg-info/dependency_links.txt
SimpleGUICS2Pygame.egg-info/requires.txt
SimpleGUICS2Pygame.egg-info/top_level.txt
SimpleGUICS2Pygame/COPYING/gpl-3.0.txt
SimpleGUICS2Pygame/_img/OPi_t.png
SimpleGUICS2Pygame/_img/SimpleGUICS2Pygame_152x261.bmp
SimpleGUICS2Pygame/_img/SimpleGUICS2Pygame_32x32.ico
SimpleGUICS2Pygame/_img/SimpleGUICS2Pygame_32x32_t.png
SimpleGUICS2Pygame/_img/SimpleGUICS2Pygame_64x64_t.png
SimpleGUICS2Pygame/_img/gplv3-88x31.png
SimpleGUICS2Pygame/example/Blackjack.py
SimpleGUICS2Pygame/example/Frame_example.py
SimpleGUICS2Pygame/example/Mandelbrot_Set.py
SimpleGUICS2Pygame/example/Memory.py
SimpleGUICS2Pygame/example/Nostalgic_Basic_Blitz.py
SimpleGUICS2Pygame/example/Pong.py
SimpleGUICS2Pygame/example/RiceRocks_Asteroids.py
SimpleGUICS2Pygame/example/Spaceship_prototype.py
SimpleGUICS2Pygame/example/Stopwatch.py
SimpleGUICS2Pygame/example/keys.py
SimpleGUICS2Pygame/example/loader.py
SimpleGUICS2Pygame/example/presentation.py
SimpleGUICS2Pygame/example/stop_example.py
SimpleGUICS2Pygame/example/Stress_Balls/Stress_Balls.py
SimpleGUICS2Pygame/example/Stress_Balls/Stress_Balls_results.py
SimpleGUICS2Pygame/example/Stress_Balls/old_results/Stress_Balls_results.png
SimpleGUICS2Pygame/example/Stress_Balls/old_results/Stress_Balls_results.svg
SimpleGUICS2Pygame/script/SimpleGUICS2Pygame_check.py
SimpleGUICS2Pygame/script/cs2both.py
SimpleGUICS2Pygame/script/pygame_check.py
SimpleGUICS2Pygame/simpleguics2pygame/__init__.py
SimpleGUICS2Pygame/simpleguics2pygame/_arguments.py
SimpleGUICS2Pygame/simpleguics2pygame/_colors.py
SimpleGUICS2Pygame/simpleguics2pygame/_fonts.py
SimpleGUICS2Pygame/simpleguics2pygame/_joypads.py
