Metadata-Version: 2.1
Name: SimpleGUICS2Pygame
Version: 2.0.3
Summary: Primarily a standard Python (2 and 3) module reimplementing the SimpleGUI particular module of CodeSkulptor (a Python browser environment). In fact a package also with other modules adapted from CodeSkulptor.
Home-page: https://simpleguics2pygame.readthedocs.io/
Author: Olivier Pirson
Author-email: olivier.pirson.opi@gmail.com
License: GPLv3
Project-URL: Documentation, https://simpleguics2pygame.readthedocs.io/
Project-URL: Funding, http://www.opimedia.be/donate/
Project-URL: Say Thanks!, http://www.opimedia.be
Project-URL: Source, https://bitbucket.org/OPiMedia/simpleguics2pygame/
Keywords: CodeSkulptor SimpleGUI Pygame game education
Platform: any
Classifier: Development Status :: 5 - Production/Stable
Classifier: Intended Audience :: Education
Classifier: Intended Audience :: End Users/Desktop
Classifier: License :: OSI Approved :: GNU General Public License v3 (GPLv3)
Classifier: Natural Language :: English
Classifier: Programming Language :: Python
Classifier: Programming Language :: Python :: 2.7
Classifier: Programming Language :: Python :: 3
Classifier: Topic :: Education
Classifier: Topic :: Games/Entertainment
Classifier: Topic :: Multimedia :: Graphics
Classifier: Topic :: Multimedia :: Sound/Audio
Classifier: Topic :: Software Development
Classifier: Topic :: Software Development :: Libraries :: pygame
Classifier: Topic :: Software Development :: Libraries :: Python Modules
Classifier: Topic :: Software Development :: User Interfaces
Classifier: Topic :: Software Development :: Widget Sets
Requires-Python: >=2.7
